hope_echo/__init__.py
hope_echo/context.py
hope_echo/core.py
hope_echo-1.0.0.dist-info/METADATA
hope_echo-1.0.0.dist-info/WHEEL
hope_echo-1.0.0.dist-info/entry_points.txt
hope_echo-1.0.0.dist-info/licenses/LICENSE
hope_echo-1.0.0.dist-info/RECORD
