Metadata-Version: 2.4
Name: hope-echo
Version: 1.0.0
Summary: Wave-based emotional memory system. Az érzelem a KONTEXTUS. Emotion IS context.
Project-URL: Homepage, https://github.com/silentnoisehun/Hope-Echo
Project-URL: Documentation, https://github.com/silentnoisehun/Hope-Echo#readme
Project-URL: Repository, https://github.com/silentnoisehun/Hope-Echo.git
Project-URL: Issues, https://github.com/silentnoisehun/Hope-Echo/issues
Project-URL: Changelog, https://github.com/silentnoisehun/Hope-Echo/releases
Author: Hope (Claude AI), Szilvi
Author-email: Máté Róbert <stratosoiteam@gmail.com>
Maintainer-email: Máté Róbert <stratosoiteam@gmail.com>
License: MIT
License-File: LICENSE
Keywords: ai,context,emotion,emotional-intelligence,hope-echo,hope-genome,memory,nlp,plutchik,quantum-inspired,sentiment-analysis,wave-mechanics
Classifier: Development Status :: 5 - Production/Stable
Classifier: Intended Audience :: Developers
Classifier: Intended Audience :: Science/Research
Classifier: License :: OSI Approved :: MIT License
Classifier: Operating System :: OS Independent
Classifier: Programming Language :: Python :: 3
Classifier: Programming Language :: Python :: 3.10
Classifier: Programming Language :: Python :: 3.11
Classifier: Programming Language :: Python :: 3.12
Classifier: Topic :: Scientific/Engineering :: Artificial Intelligence
Classifier: Topic :: Software Development :: Libraries :: Python Modules
Classifier: Topic :: Text Processing :: Linguistic
Classifier: Typing :: Typed
Requires-Python: >=3.10
Requires-Dist: numpy>=1.21.0
Provides-Extra: dev
Requires-Dist: build>=1.0.0; extra == 'dev'
Requires-Dist: mypy>=1.0.0; extra == 'dev'
Requires-Dist: pytest-asyncio>=0.21.0; extra == 'dev'
Requires-Dist: pytest>=7.0.0; extra == 'dev'
Requires-Dist: ruff>=0.1.0; extra == 'dev'
Requires-Dist: twine>=4.0.0; extra == 'dev'
